oilgas_analysis/__init__.py
oilgas_analysis/artificial_lift.py
oilgas_analysis/ipr_curves.py
oilgas_analysis/reservoir_prediction.py
oilgas_analysis/well_logs.py
tests/__init__.py
tests/test_artificial_lift.py
tests/test_reservoir_prediction.py
tests/test_well_logs.py
oilgas_analysis-0.1.0.dist-info/METADATA
oilgas_analysis-0.1.0.dist-info/WHEEL
oilgas_analysis-0.1.0.dist-info/top_level.txt
oilgas_analysis-0.1.0.dist-info/RECORD
