Metadata-Version: 2.1
Name: oilgas_analysis
Version: 0.1.0
Summary: A package for oil and gas well analysis
Home-page: https://github.com/shailesh2790/oilgas_analysis
Author: Shailesh Tripathi
Author-email: tripathi_shailesh@ongc.co.in
Classifier: Programming Language :: Python :: 3
Classifier: License :: OSI Approved :: MIT License
Classifier: Operating System :: OS Independent
Requires-Python: >=3.6
Requires-Dist: numpy
Requires-Dist: pandas
Requires-Dist: matplotlib
Requires-Dist: scipy
